bretina/__init__.py
bretina/imagestitcher.py
bretina/polyline.py
bretina/visualtestcase.py
bretina-0.7.6.dist-info/LICENSE
bretina-0.7.6.dist-info/METADATA
bretina-0.7.6.dist-info/WHEEL
bretina-0.7.6.dist-info/top_level.txt
bretina-0.7.6.dist-info/RECORD
