Metadata-Version: 2.1
Name: bretina
Version: 0.7.6
Summary: Bender Robotics Visual Test Support
Home-page: https://www.benderrobotics.com
Author: Bender Robotics
Author-email: kumpan@benderrobotics.com
License: UNKNOWN
Platform: UNKNOWN
Classifier: Programming Language :: Python :: 3
Classifier: License :: OSI Approved :: MIT License
Classifier: Operating System :: OS Independent
Requires-Python: >=3.6
License-File: LICENSE
Requires-Dist: opencv-python>=4.1.1.0
Requires-Dist: numpy>=1.17
Requires-Dist: pytesseract<=0.3.10,>=0.3.0
Requires-Dist: Pillow>=6.2.1
Requires-Dist: htmllogging>=0.0.1
